{
	"credit": "Made with Blockbench",
	"texture_size": [1000, 320],
	"textures": {
		"0": "item/texts/lyrics/text"
	},
	"elements": [
		{
			"from": [10.2, 0.2, 6.9],
			"to": [13.4, 4.2, 9.1],
			"rotation": {"angle": 0, "axis": "y", "origin": [8, 0, 8]},
			"faces": {
				"north": {"uv": [6.752, 1.1, 7.264, 3.1], "texture": "#0"},
				"south": {"uv": [7.264, 1.1, 6.752, 3.1], "texture": "#0"},
				"up": {"uv": [7.264, 1.1, 6.752, 0], "texture": "#0"},
				"down": {"uv": [7.264, 4.2, 6.752, 3.1], "texture": "#0"}
			}
		},
		{
			"from": [11.6, 3.6, 6.7],
			"to": [12, 4.4, 9.3],
			"rotation": {"angle": 0, "axis": "y", "origin": [8, 0, 8]},
			"faces": {
				"east": {"uv": [0, 13.3, 0.016, 13.35], "texture": "#0"},
				"west": {"uv": [0, 13.3, 0.016, 13.35], "texture": "#0"},
				"down": {"uv": [0, 13.3, 0.016, 13.35], "texture": "#0"}
			}
		},
		{
			"from": [11.6, 0, 6.7],
			"to": [12, 1, 9.3],
			"rotation": {"angle": 0, "axis": "y", "origin": [8, 0, 8]},
			"faces": {
				"east": {"uv": [0, 13.3, 0.016, 13.35], "texture": "#0"},
				"west": {"uv": [0, 13.3, 0.016, 13.35], "texture": "#0"},
				"up": {"uv": [0, 13.3, 0.016, 13.35], "texture": "#0"}
			}
		},
		{
			"from": [13.6, 4.4, 9.3],
			"to": [10, 0, 6.7],
			"rotation": {"angle": 0, "axis": "y", "origin": [8, 0, 8]},
			"faces": {
				"north": {"uv": [0.304, 14.4, 0.448, 13.3], "texture": "#0"},
				"east": {"uv": [0, 13.3, 0.016, 13.35], "texture": "#0"},
				"south": {"uv": [0.304, 14.4, 0.448, 13.3], "texture": "#0"},
				"west": {"uv": [0, 13.3, 0.016, 13.35], "texture": "#0"},
				"up": {"uv": [0.304, 13.3, 0.448, 13.35], "texture": "#0"},
				"down": {"uv": [0.304, 13.3, 0.448, 13.35], "texture": "#0"}
			}
		},
		{
			"from": [7, 0.2, 6.9],
			"to": [9.8, 4.2, 9.1],
			"rotation": {"angle": 0, "axis": "y", "origin": [8, 0, 8]},
			"faces": {
				"north": {"uv": [7.296, 1.1, 7.744, 3.1], "texture": "#0"},
				"south": {"uv": [7.744, 1.1, 7.296, 3.1], "texture": "#0"},
				"up": {"uv": [7.744, 1.1, 7.296, 0], "texture": "#0"},
				"down": {"uv": [7.744, 4.2, 7.296, 3.1], "texture": "#0"}
			}
		},
		{
			"from": [10, 4.4, 9.3],
			"to": [6.8, 0, 6.7],
			"rotation": {"angle": 0, "axis": "y", "origin": [8, 0, 8]},
			"faces": {
				"north": {"uv": [0, 13.3, 0.016, 13.35], "texture": "#0"},
				"east": {"uv": [0, 13.3, 0.016, 13.35], "texture": "#0"},
				"south": {"uv": [0, 13.3, 0.016, 13.35], "texture": "#0"},
				"west": {"uv": [0, 13.3, 0.016, 13.35], "texture": "#0"},
				"up": {"uv": [0, 13.3, 0.016, 13.35], "texture": "#0"},
				"down": {"uv": [0, 13.3, 0.016, 13.35], "texture": "#0"}
			}
		},
		{
			"from": [2.6, 0.2, 6.9],
			"to": [6.6, 4.2, 9.1],
			"rotation": {"angle": 0, "axis": "y", "origin": [8, 0, 8]},
			"faces": {
				"north": {"uv": [11.2, 1.1, 11.84, 3.1], "texture": "#0"},
				"east": {"uv": [0.032, 13.3, 0.048, 13.4], "texture": "#0"},
				"south": {"uv": [11.84, 1.1, 11.2, 3.1], "texture": "#0"},
				"west": {"uv": [0.032, 13.3, 0.048, 13.4], "texture": "#0"},
				"up": {"uv": [11.84, 1.1, 11.2, 0], "texture": "#0"},
				"down": {"uv": [11.84, 4.2, 11.2, 3.1], "texture": "#0"}
			}
		},
		{
			"from": [4.2, 3, 6.9],
			"to": [5, 3, 9.1],
			"rotation": {"angle": 0, "axis": "y", "origin": [8, 0, 8]},
			"faces": {
				"up": {"uv": [12, 1.1, 11.872, 0], "texture": "#0"}
			}
		},
		{
			"from": [4, 3.2, 6.7],
			"to": [5.2, 4.4, 9.3],
			"rotation": {"angle": 0, "axis": "y", "origin": [8, 0, 8]},
			"faces": {
				"east": {"uv": [0, 13.3, 0.016, 13.35], "texture": "#0"},
				"west": {"uv": [0, 13.3, 0.016, 13.35], "texture": "#0"},
				"down": {"uv": [0, 13.3, 0.016, 13.35], "texture": "#0"}
			}
		},
		{
			"from": [4.4, 0, 6.7],
			"to": [4.8, 1.2, 9.3],
			"rotation": {"angle": 0, "axis": "y", "origin": [8, 0, 8]},
			"faces": {
				"east": {"uv": [0, 13.3, 0.016, 13.35], "texture": "#0"},
				"west": {"uv": [0, 13.3, 0.016, 13.35], "texture": "#0"},
				"up": {"uv": [0, 13.3, 0.016, 13.35], "texture": "#0"}
			}
		},
		{
			"from": [6.4, 0, 6.7],
			"to": [6.8, 0.8, 9.3],
			"rotation": {"angle": 0, "axis": "y", "origin": [8, 0, 8]},
			"faces": {
				"west": {"uv": [0, 13.3, 0.016, 13.35], "texture": "#0"},
				"up": {"uv": [0, 13.3, 0.016, 13.35], "texture": "#0"}
			}
		},
		{
			"from": [2.4, 0, 6.7],
			"to": [2.8, 0.8, 9.3],
			"rotation": {"angle": 0, "axis": "y", "origin": [8, 0, 8]},
			"faces": {
				"east": {"uv": [0, 13.3, 0.016, 13.35], "texture": "#0"},
				"up": {"uv": [0, 13.3, 0.016, 13.35], "texture": "#0"}
			}
		},
		{
			"from": [6.8, 4.4, 9.3],
			"to": [2.4, 0, 6.7],
			"rotation": {"angle": 0, "axis": "y", "origin": [8, 0, 8]},
			"faces": {
				"north": {"uv": [0.448, 13.85, 0.624, 13.3], "texture": "#0"},
				"east": {"uv": [0.448, 13.85, 0.464, 13.3], "texture": "#0"},
				"south": {"uv": [0.448, 13.85, 0.624, 13.3], "texture": "#0"},
				"west": {"uv": [0.448, 13.85, 0.464, 13.3], "texture": "#0"},
				"up": {"uv": [0.448, 13.85, 0.624, 13.8], "texture": "#0"},
				"down": {"uv": [0.448, 13.35, 0.624, 13.3], "texture": "#0"}
			}
		}
	],
	"groups": [
		{
			"name": "now",
			"origin": [8, 0, 8],
			"color": 0,
			"children": [
				{
					"name": "n",
					"origin": [8, 0, 8],
					"color": 0,
					"children": [0, 1, 2, 3]
				},
				{
					"name": "o",
					"origin": [8, 0, 8],
					"color": 0,
					"children": [4, 5]
				},
				{
					"name": "w",
					"origin": [8, 0, 8],
					"color": 0,
					"children": [6, 7, 8, 9, 10, 11, 12]
				}
			]
		}
	]
}